discordpythonv2/__init__.py
discordpythonv2/setup.py
discordpythonv2-0.0.1.dist-info/METADATA
discordpythonv2-0.0.1.dist-info/WHEEL
discordpythonv2-0.0.1.dist-info/top_level.txt
discordpythonv2-0.0.1.dist-info/RECORD
